naotool/__init__.py
naotool/__version__.py
naotool/cls/__init__.py
naotool/deco/__init__.py
naotool/deco/compat.py
naotool/deco/deco.py
naotool/deco/funtool.py
naotool/exception.py
naotool/httpn/__init__.py
naotool/img/__init__.py
naotool/img/gets.py
naotool/img/op.py
naotool/strs/__init__.py
naotool/x/__init__.py
naotool/x/client.py
naotool/x/xpostx.py
naotool-0.3.4.dist-info/LICENSE
naotool-0.3.4.dist-info/METADATA
naotool-0.3.4.dist-info/WHEEL
naotool-0.3.4.dist-info/RECORD
