Metadata-Version: 2.1
Name: naotool
Version: 0.3.4
Summary: A packge of utils or tools keeps Python sweet.
Home-page: https://github.com/tomorinao-www/naotool
License: MIT
Author: tomorinao-www
Author-email: 1520872279@qq.com
Requires-Python: >=3.10
Classifier: License :: OSI Approved :: MIT License
Classifier: Programming Language :: Python :: 3
Classifier: Programming Language :: Python :: 3.10
Classifier: Programming Language :: Python :: 3.11
Classifier: Programming Language :: Python :: 3.12
Classifier: Programming Language :: Python :: 3.13
Requires-Dist: httpx (>=0.27.2)
Requires-Dist: httpx-auth (>=0.22.0)
Requires-Dist: oauthlib (>=3.2.2)
Requires-Dist: pillow (>=8.0.0)
Requires-Dist: playwright (>=1.49.0)
Requires-Dist: typeguard (>=4.3.0)
Project-URL: Documentation, https://github.com/tomorinao-www/naotool#README.md
Project-URL: Issue Tracker, https://github.com/tomorinao-www/naotool/issues
Project-URL: Repository, https://github.com/tomorinao-www/naotool
